avito/__init__.py
avito/avito.py
avito-0.0.3.data/data/my_data/data_file
avito-0.0.3.dist-info/DESCRIPTION.rst
avito-0.0.3.dist-info/METADATA
avito-0.0.3.dist-info/RECORD
avito-0.0.3.dist-info/WHEEL
avito-0.0.3.dist-info/entry_points.txt
avito-0.0.3.dist-info/metadata.json
avito-0.0.3.dist-info/top_level.txt
tests/__init__.py
tests/test_simple.py
